cpm/__init__.py
cpm/__main__.py
cpm/client.py
cpm/command.py
cpm/logging.py
cpm/settings.py
cpm/logs/__init__.py
cpm_aids-0.1.2.data/scripts/cpm
cpm_aids-0.1.2.data/scripts/cpm.bin
cpm_aids-0.1.2.dist-info/LICENSE
cpm_aids-0.1.2.dist-info/METADATA
cpm_aids-0.1.2.dist-info/WHEEL
cpm_aids-0.1.2.dist-info/top_level.txt
cpm_aids-0.1.2.dist-info/RECORD
