Metadata-Version: 2.1
Name: cpm-aids
Version: 0.1.2
Summary: Card Package Manager
Home-page: https://github.com/Moist-Cat/cpm
Author: Moist-Cat
Author-email: moistanonpy@gmail.com
Classifier: Programming Language :: Python :: 3
Classifier: License :: OSI Approved :: MIT License
Requires-Python: >=3
License-File: LICENSE
Requires-Dist: requests (==2.*)
Requires-Dist: pyaml
